carbonation/__about__.py
carbonation/__init__.py
carbonation/utils.py
carbonation/cli/__init__.py
carbonation/cli/utils.py
carbonation/cli/measurand/__init__.py
carbonation/cli/measurand/__main__.py
carbonation/cli/reframe/__init__.py
carbonation/cli/reframe/__main__.py
carbonation/measurand/__init__.py
carbonation/measurand/component.py
carbonation/measurand/euc.py
carbonation/measurand/generic.py
carbonation/measurand/interp.py
carbonation/measurand/measurand.py
carbonation/measurand/parameter.py
carbonation/measurand/sampling.py
carbonation/measurand/utils.py
carbonation-0.1.1.dist-info/METADATA
carbonation-0.1.1.dist-info/WHEEL
carbonation-0.1.1.dist-info/entry_points.txt
carbonation-0.1.1.dist-info/licenses/LICENSE.txt
carbonation-0.1.1.dist-info/RECORD
