Metadata-Version: 2.3
Name: carbonation
Version: 0.1.1
Summary: You can't have fizz without carbonation
Project-URL: Documentation, https://github.com/jolsten/carbonation#readme
Project-URL: Issues, https://github.com/jolsten/carbonation/issues
Project-URL: Source, https://github.com/jolsten/carbonation
Author-email: Jonathan Olsten <jonathan.olsten@gmail.com>
License-Expression: MIT
License-File: LICENSE.txt
Classifier: Development Status :: 4 - Beta
Classifier: Programming Language :: Python
Classifier: Programming Language :: Python :: 3.8
Classifier: Programming Language :: Python :: 3.9
Classifier: Programming Language :: Python :: 3.10
Classifier: Programming Language :: Python :: 3.11
Classifier: Programming Language :: Python :: 3.12
Classifier: Programming Language :: Python :: Implementation :: CPython
Classifier: Programming Language :: Python :: Implementation :: PyPy
Requires-Python: >=3.8
Requires-Dist: numba>=0.57
Requires-Dist: numpy<1.26,>=1.19
Requires-Dist: pyarrow>=7.0.0
Requires-Dist: pydantic>=2.0
Requires-Dist: typeconvert==0.2
Provides-Extra: cli
Requires-Dist: python-dateutil; extra == 'cli'
